kinetic/__init__.py
kinetic/generate.py
project_kinetic-1.0.3.dist-info/LICENSE
project_kinetic-1.0.3.dist-info/METADATA
project_kinetic-1.0.3.dist-info/WHEEL
project_kinetic-1.0.3.dist-info/top_level.txt
project_kinetic-1.0.3.dist-info/RECORD
