Metadata-Version: 2.1
Name: project-kinetic
Version: 1.0.3
Summary: Control modular and configurable robotic agents over the network.
Home-page: https://github.com/perpetualCreations/swbs/
Author: perpetualCreations
Author-email: tchen0584@gmail.com
License: UNKNOWN
Platform: UNKNOWN
Classifier: Programming Language :: Python :: 3
Classifier: License :: OSI Approved :: MIT License
Classifier: Operating System :: OS Independent
Requires-Python: >=3.6
Requires-Dist: swbs (>1.2)
Requires-Dist: pyserial
Requires-Dist: numpy
Requires-Dist: opencv-contrib-python
Requires-Dist: imutils
Requires-Dist: sense-hat
Requires-Dist: gpiozero
